design_config/__init__.py
design_config-0.0.8.dist-info/LICENSE
design_config-0.0.8.dist-info/METADATA
design_config-0.0.8.dist-info/WHEEL
design_config-0.0.8.dist-info/top_level.txt
design_config-0.0.8.dist-info/RECORD
