Metadata-Version: 2.1
Name: design_config
Version: 0.0.8
Summary: Smart tiny config library for flask-like config
Home-page: https://github.com/artmihant/design_config
Author: Artem Antonov
Author-email: Artem Antonov <artmihant@gmail.com>
Project-URL: Homepage, https://github.com/artmihant/design_config
Project-URL: Bug Tracker, https://github.com/artmihant/design_config/issues
Classifier: Programming Language :: Python :: 3
Classifier: License :: OSI Approved :: MIT License
Classifier: Operating System :: OS Independent
Classifier: Development Status :: 3 - Alpha
Classifier: Intended Audience :: Developers
Requires-Python: >=3.6
License-File: LICENSE
